admin_locking/__init__.py
admin_locking/admin.py
admin_locking/locale/de/LC_MESSAGES/django.mo
admin_locking/locale/de/LC_MESSAGES/django.po
admin_locking/static/admin_locking/admin_locking.js
django_admin_locking-0.10.0.dist-info/LICENSE.txt
django_admin_locking-0.10.0.dist-info/METADATA
django_admin_locking-0.10.0.dist-info/WHEEL
django_admin_locking-0.10.0.dist-info/top_level.txt
django_admin_locking-0.10.0.dist-info/RECORD
